vijil_cli/__init__.py
vijil_cli/__main__.py
vijil_cli/cli.py
vijil_cli-0.1.0.dist-info/METADATA
vijil_cli-0.1.0.dist-info/WHEEL
vijil_cli-0.1.0.dist-info/entry_points.txt
vijil_cli-0.1.0.dist-info/RECORD
