Metadata-Version: 2.1
Name: vijil-cli
Version: 0.1.0
Summary: Vijil CLI for interacting with Vijil
Author: Vijilai
Author-email: your.email@example.com
Requires-Python: >=3.9,<4.0
Classifier: Programming Language :: Python :: 3
Classifier: Programming Language :: Python :: 3.9
Classifier: Programming Language :: Python :: 3.10
Classifier: Programming Language :: Python :: 3.11
Classifier: Programming Language :: Python :: 3.12
Requires-Dist: python-dotenv (>=1.0.0,<2.0.0)
Requires-Dist: requests (>=2.26.0,<3.0.0)
